seqdist/__init__.py
seqdist/_nbdev.py
seqdist/core.py
seqdist/ctc.py
seqdist/ctc_banded.py
seqdist/ctc_simple.py
seqdist/normalisation.py
seqdist/sparse.py
seqdist/utils.py
seqdist/cuda/ctc.cu
seqdist/cuda/ctc_banded.cu
seqdist/cuda/ctc_simple.cu
seqdist/cuda/fused_bmv.cu
seqdist/cuda/sparse.cu
seqdist/cuda/sparse_logZ.cu
seqdist/cuda/sparse_scan.cu
seqdist-0.0.3.dist-info/LICENSE
seqdist-0.0.3.dist-info/METADATA
seqdist-0.0.3.dist-info/WHEEL
seqdist-0.0.3.dist-info/entry_points.txt
seqdist-0.0.3.dist-info/top_level.txt
seqdist-0.0.3.dist-info/RECORD
